dbrhino_agent/__init__.py
dbrhino_agent/__main__.py
dbrhino_agent/config.py
dbrhino_agent/dbrhino.py
dbrhino_agent/interactive.py
dbrhino_agent/templates.py
dbrhino_agent/version.py
dbrhino_agent/db/__init__.py
dbrhino_agent/db/common.py
dbrhino_agent/db/mysql.py
dbrhino_agent/db/postgresql.py
dbrhino_agent-0.3.5.dist-info/DESCRIPTION.rst
dbrhino_agent-0.3.5.dist-info/METADATA
dbrhino_agent-0.3.5.dist-info/RECORD
dbrhino_agent-0.3.5.dist-info/WHEEL
dbrhino_agent-0.3.5.dist-info/entry_points.txt
dbrhino_agent-0.3.5.dist-info/metadata.json
dbrhino_agent-0.3.5.dist-info/top_level.txt
