Metadata-Version: 2.0
Name: dbrhino-agent
Version: 0.3.5
Summary: Agent for dbrhino
Home-page: https://dbrhino.com
Author: Buck Ryan
Author-email: UNKNOWN
License: UNKNOWN
Platform: UNKNOWN
Classifier: Programming Language :: Python :: 3 :: Only
Requires-Dist: click (<7,>=6)
Requires-Dist: requests (<3,>=2)
Requires-Dist: PyMySQL (<1)
Requires-Dist: psycopg2 (<3,>=2)
Requires-Dist: jinja2
Requires-Dist: sqlparse
Requires-Dist: daemonize
